{
    "groups": [
        {
            "sourceType": "com.github.mybatisx.spring.boot.pageable.config.MyBatisPageableProperties",
            "name": "wvkity.mybatis.plugin.pageable",
            "type": "com.github.mybatisx.spring.boot.pageable.config.MyBatisPageableProperties"
        },
        {
            "sourceType": "com.github.mybatisx.spring.boot.pageable.config.MyBatisPageableProperties",
            "name": "wvkity.mybatis.plugin.pageable.properties",
            "sourceMethod": "getProperties()",
            "type": "java.util.Properties"
        }
    ]
}
